[
  {
    "nome": "Tintim",
    "img": "https://static.wikia.nocookie.net/dublagem/images/6/63/Tintim.jpg/revision/latest?cb=20240623151337&path-prefix=pt-br",
    "pasta": "a/as-aventuras-de-tintim-dublado",
    "total": 39
  },
  {
    "nome": "Yomi",
    "img": "https://imgsrv.crunchyroll.com/cdn-cgi/image/fit=contain,format=auto,quality=85,width=1200,height=675/catalog/crunchyroll/cf01037046bf9885e1ddbc3c1753610e.png",
    "pasta": "y/yomi-no-tsugai",
    "total": 12
  },
  {
    "nome": "Invencivel",
    "img": "https://i.ytimg.com/vi/Xg8aWV14vSs/maxresdefault.jpg",
    "pasta": "i/invencivel-4-dublado",
    "total": 8
  },
  {
    "nome": "Pantera",
    "img": "https://encrypted-tbn0.gstatic.com/images?q=tbn:ANd9GcTKlP0fX0wkJMcFT5d2lKmz8j0iBPgHq7wIwBlLfBQbCA&s=10",
    "pasta": "a/a-pantera-cor-de-rosa",
    "total": 129
  },
  {
    "nome": "One Piece",
    "img": "https://m.media-amazon.com/images/M/MV5BMTNjNGU4NTUtYmVjMy00YjRiLTkxMWUtNzZkMDNiYjZhNmViXkEyXkFqcGc@._V1_FMjpg_UX1000_.jpg",
    "pasta": "o/one-piece",
    "total": 1167,
    "start": 1003
  }
]